tox_no_internet.py
tox_no_internet-0.1.0.dist-info/DESCRIPTION.rst
tox_no_internet-0.1.0.dist-info/METADATA
tox_no_internet-0.1.0.dist-info/RECORD
tox_no_internet-0.1.0.dist-info/WHEEL
tox_no_internet-0.1.0.dist-info/entry_points.txt
tox_no_internet-0.1.0.dist-info/metadata.json
tox_no_internet-0.1.0.dist-info/top_level.txt
