Metadata-Version: 2.0
Name: tox-no-internet
Version: 0.1.0
Summary: Workarounds for using tox with no internet connection
Home-page: https://github.com/lulupac/tox-no-internet
Author: lulupac
Author-email: lulupac07@gmail.com
License: UNKNOWN
Platform: UNKNOWN
Classifier: License :: OSI Approved :: MIT License
Classifier: Programming Language :: Python :: 2
Classifier: Programming Language :: Python :: 2.7
Classifier: Programming Language :: Python :: 3
Classifier: Programming Language :: Python :: Implementation :: CPython
Requires-Dist: tox (>=2.7)
